codomir/__init__.py
codomir/quest.py
codomir/maps/__init__.py
codomir/maps/linear.py
codomir/maps/loop.py
codomir/maps/nested_loops.py
codomir/resources/__init__.py
codomir/resources/resolve_path.py
codomir/resources/kenney_sokoban/License.txt
codomir/resources/kenney_sokoban/map1.tiled-project
codomir/resources/kenney_sokoban/map1.tiled-session
codomir/resources/kenney_sokoban/map1.tmx
codomir/resources/kenney_sokoban/map10.tmx
codomir/resources/kenney_sokoban/map2.tmx
codomir/resources/kenney_sokoban/map3.tmx
codomir/resources/kenney_sokoban/map4.tmx
codomir/resources/kenney_sokoban/map5.tmx
codomir/resources/kenney_sokoban/map6.tmx
codomir/resources/kenney_sokoban/map_loop1.tmx
codomir/resources/kenney_sokoban/map_loop2.tmx
codomir/resources/kenney_sokoban/map_loop3.tmx
codomir/resources/kenney_sokoban/map_loop4.tmx
codomir/resources/kenney_sokoban/map_loop5.tmx
codomir/resources/kenney_sokoban/map_loop6.tmx
codomir/resources/kenney_sokoban/map_loop_nested1.tmx
codomir/resources/kenney_sokoban/map_loop_nested2.tmx
codomir/resources/kenney_sokoban/sokoban_tilesheet.tsx
codomir/resources/kenney_sokoban/Spritesheet/sokoban_spritesheet.png
codomir/resources/kenney_sokoban/Spritesheet/sokoban_spritesheet.xml
codomir/resources/kenney_sokoban/Spritesheet/sokoban_spritesheet@2.png
codomir/resources/kenney_sokoban/Spritesheet/sokoban_spritesheet@2.xml
codomir/resources/kenney_sokoban/Tilesheet/sokoban_tilesheet.png
codomir/resources/kenney_sokoban/Tilesheet/sokoban_tilesheet@2.png
pygamejr/__init__.py
pygamejr/base.py
pygamejr/scene.py
pygamejr/tilemap.py
pygamejr/resources/__init__.py
pygamejr/resources/image.py
pygamejr/resources/image_tanks.py
pygamejr/resources/resolve_path.py
pygamejr/resources/images/License.txt
pygamejr/resources/images/readme.txt
pygamejr/resources/images/enemies/bee.png
pygamejr/resources/images/enemies/fishGreen.png
pygamejr/resources/images/enemies/fishPink.png
pygamejr/resources/images/enemies/fly.png
pygamejr-0.0.17.dist-info/METADATA
pygamejr-0.0.17.dist-info/WHEEL
pygamejr-0.0.17.dist-info/licenses/LICENSE
pygamejr-0.0.17.dist-info/RECORD
