Metadata-Version: 2.4
Name: pygamejr
Version: 0.0.17
Summary: Simple PyGame extension for education.
Project-URL: Homepage, https://github.com/benefitkids/pygamejr
Project-URL: Issues, https://github.com/benefitkids/pygamejr/issues
Author-email: Alexander Mironov <miralexander@gmail.com>
License-Expression: MIT
License-File: LICENSE
Classifier: Operating System :: OS Independent
Classifier: Programming Language :: Python :: 3
Requires-Python: >=3.8
Requires-Dist: pygame-ce
Requires-Dist: pytmx
